{
  "summary": {
    "model": "gemma-2-27B",
    "difficulty": "easy",
    "question_type": "group",
    "total_samples": 100,
    "correct_predictions": 32,
    "accuracy": 32.0
  },
  "results": [
    {
      "sample_id": 0,
      "difficulty": "unknown",
      "question_type": "group",
      "true_answer": "A, B, C, D, F",
      "prediction": "A",
      "correct": false,
      "response": "Final Answer: A \n"
    },
    {
      "sample_id": 3,
      "difficulty": "unknown",
      "question_type": "group",
      "true_answer": "A, F, G",
      "prediction": "A, F",
      "correct": false,
      "response": "Final Answer: A, F \n"
    },
    {
      "sample_id": 2,
      "difficulty": "unknown",
      "question_type": "group",
      "true_answer": "C, D",
      "prediction": "C",
      "correct": false,
      "response": "Final Answer: C \n"
    },
    {
      "sample_id": 6,
      "difficulty": "unknown",
      "question_type": "group",
      "true_answer": "B, D, G",
      "prediction": "B",
      "correct": false,
      "response": "Final Answer: B \n"
    },
    {
      "sample_id": 1,
      "difficulty": "unknown",
      "question_type": "group",
      "true_answer": "A, B, D, E",
      "prediction": "A, B",
      "correct": false,
      "response": "Final Answer: A, B \n"
    },
    {
      "sample_id": 8,
      "difficulty": "unknown",
      "question_type": "group",
      "true_answer": "C",
      "prediction": "C",
      "correct": true,
      "response": "Final Answer: C \n"
    },
    {
      "sample_id": 5,
      "difficulty": "unknown",
      "question_type": "group",
      "true_answer": "D",
      "prediction": "D",
      "correct": true,
      "response": "Final Answer: D \n"
    },
    {
      "sample_id": 9,
      "difficulty": "unknown",
      "question_type": "group",
      "true_answer": "A, B, D",
      "prediction": "A, D",
      "correct": false,
      "response": "Final Answer: A, D \n"
    },
    {
      "sample_id": 4,
      "difficulty": "unknown",
      "question_type": "group",
      "true_answer": "B, E, H, J",
      "prediction": "B",
      "correct": false,
      "response": "Final Answer: B \n"
    },
    {
      "sample_id": 7,
      "difficulty": "unknown",
      "question_type": "group",
      "true_answer": "D, E, F, G, J",
      "prediction": "D, G, J",
      "correct": false,
      "response": "Final Answer: D, G, J \n"
    },
    {
      "sample_id": 11,
      "difficulty": "unknown",
      "question_type": "group",
      "true_answer": "D, E, H",
      "prediction": "D",
      "correct": false,
      "response": "Final Answer: D \n"
    },
    {
      "sample_id": 10,
      "difficulty": "unknown",
      "question_type": "group",
      "true_answer": "A",
      "prediction": "A",
      "correct": true,
      "response": "Final Answer: A \n"
    },
    {
      "sample_id": 12,
      "difficulty": "unknown",
      "question_type": "group",
      "true_answer": "E, G, H",
      "prediction": "H",
      "correct": false,
      "response": "Final Answer: H \n"
    },
    {
      "sample_id": 13,
      "difficulty": "unknown",
      "question_type": "group",
      "true_answer": "B, E, F",
      "prediction": "B",
      "correct": false,
      "response": "Final Answer: B \n"
    },
    {
      "sample_id": 14,
      "difficulty": "unknown",
      "question_type": "group",
      "true_answer": "A, B, C, G, H",
      "prediction": "A",
      "correct": false,
      "response": "Final Answer: A \n"
    },
    {
      "sample_id": 17,
      "difficulty": "unknown",
      "question_type": "group",
      "true_answer": "C, D, H",
      "prediction": "C",
      "correct": false,
      "response": "Final Answer: C \n"
    },
    {
      "sample_id": 19,
      "difficulty": "unknown",
      "question_type": "group",
      "true_answer": "A, E",
      "prediction": "E",
      "correct": false,
      "response": "Final Answer: E \n"
    },
    {
      "sample_id": 18,
      "difficulty": "unknown",
      "question_type": "group",
      "true_answer": "F, H",
      "prediction": "F, H",
      "correct": true,
      "response": "Final Answer: F, H \n"
    },
    {
      "sample_id": 15,
      "difficulty": "unknown",
      "question_type": "group",
      "true_answer": "C, F",
      "prediction": "A, C, H",
      "correct": false,
      "response": "Final Answer: A, C, H \n"
    },
    {
      "sample_id": 16,
      "difficulty": "unknown",
      "question_type": "group",
      "true_answer": "A, C, D, E, F, H",
      "prediction": "A, E, F, H",
      "correct": false,
      "response": "Final Answer: A, E, F, H \n"
    },
    {
      "sample_id": 20,
      "difficulty": "unknown",
      "question_type": "group",
      "true_answer": "D, E, G",
      "prediction": "D, E, G",
      "correct": true,
      "response": "Final Answer: D, E, G \n"
    },
    {
      "sample_id": 21,
      "difficulty": "unknown",
      "question_type": "group",
      "true_answer": "A, H",
      "prediction": "H",
      "correct": false,
      "response": "Final Answer: H \n"
    },
    {
      "sample_id": 22,
      "difficulty": "unknown",
      "question_type": "group",
      "true_answer": "A, B, C, G",
      "prediction": "A",
      "correct": false,
      "response": "Final Answer: A \n"
    },
    {
      "sample_id": 25,
      "difficulty": "unknown",
      "question_type": "group",
      "true_answer": "B, F, G",
      "prediction": "B",
      "correct": false,
      "response": "Final Answer: B \n"
    },
    {
      "sample_id": 27,
      "difficulty": "unknown",
      "question_type": "group",
      "true_answer": "D",
      "prediction": "D",
      "correct": true,
      "response": "Final Answer: D \n"
    },
    {
      "sample_id": 28,
      "difficulty": "unknown",
      "question_type": "group",
      "true_answer": "G, H",
      "prediction": "H",
      "correct": false,
      "response": "Final Answer: H \n"
    },
    {
      "sample_id": 23,
      "difficulty": "unknown",
      "question_type": "group",
      "true_answer": "A, F, H",
      "prediction": "A, F, H",
      "correct": true,
      "response": "Final Answer: A, F, H \n"
    },
    {
      "sample_id": 29,
      "difficulty": "unknown",
      "question_type": "group",
      "true_answer": "A, C, F, H",
      "prediction": "A",
      "correct": false,
      "response": "Final Answer: A \n"
    },
    {
      "sample_id": 26,
      "difficulty": "unknown",
      "question_type": "group",
      "true_answer": "E, F",
      "prediction": "E, F",
      "correct": true,
      "response": "Final Answer: E, F \n"
    },
    {
      "sample_id": 24,
      "difficulty": "unknown",
      "question_type": "group",
      "true_answer": "C, E, H",
      "prediction": "C",
      "correct": false,
      "response": "Final Answer: C \n"
    },
    {
      "sample_id": 30,
      "difficulty": "unknown",
      "question_type": "group",
      "true_answer": "B, F",
      "prediction": "B",
      "correct": false,
      "response": "Final Answer: B \n"
    },
    {
      "sample_id": 32,
      "difficulty": "unknown",
      "question_type": "group",
      "true_answer": "A, H",
      "prediction": "H",
      "correct": false,
      "response": "Final Answer: H \n"
    },
    {
      "sample_id": 31,
      "difficulty": "unknown",
      "question_type": "group",
      "true_answer": "A, C, H",
      "prediction": "H",
      "correct": false,
      "response": "Final Answer: H \n"
    },
    {
      "sample_id": 33,
      "difficulty": "unknown",
      "question_type": "group",
      "true_answer": "B, G, I",
      "prediction": "B, G",
      "correct": false,
      "response": "Final Answer: B, G \n"
    },
    {
      "sample_id": 35,
      "difficulty": "unknown",
      "question_type": "group",
      "true_answer": "B",
      "prediction": "B",
      "correct": true,
      "response": "Final Answer: B \n"
    },
    {
      "sample_id": 38,
      "difficulty": "unknown",
      "question_type": "group",
      "true_answer": "C, E, H",
      "prediction": "H",
      "correct": false,
      "response": "Final Answer: H \n"
    },
    {
      "sample_id": 39,
      "difficulty": "unknown",
      "question_type": "group",
      "true_answer": "B, E, F, G",
      "prediction": "B",
      "correct": false,
      "response": "Final Answer: B \n"
    },
    {
      "sample_id": 37,
      "difficulty": "unknown",
      "question_type": "group",
      "true_answer": "A, C, H, J",
      "prediction": "A",
      "correct": false,
      "response": "Final Answer: A \n"
    },
    {
      "sample_id": 34,
      "difficulty": "unknown",
      "question_type": "group",
      "true_answer": "A, E, F, J",
      "prediction": "A, E, J",
      "correct": false,
      "response": "Final Answer: A, E, J \n"
    },
    {
      "sample_id": 36,
      "difficulty": "unknown",
      "question_type": "group",
      "true_answer": "D, E, F, H, I",
      "prediction": "D, E, F, I, H",
      "correct": true,
      "response": "Final Answer: D, E, F, I, H \n"
    },
    {
      "sample_id": 40,
      "difficulty": "unknown",
      "question_type": "group",
      "true_answer": "A, B, F, H",
      "prediction": "A, B, F, H",
      "correct": true,
      "response": "Final Answer: A, B, F, H \n"
    },
    {
      "sample_id": 41,
      "difficulty": "unknown",
      "question_type": "group",
      "true_answer": "B, D, F, G, H",
      "prediction": "B, D",
      "correct": false,
      "response": "Final Answer: B, D \n"
    },
    {
      "sample_id": 43,
      "difficulty": "unknown",
      "question_type": "group",
      "true_answer": "G",
      "prediction": "G",
      "correct": true,
      "response": "Final Answer: G \n"
    },
    {
      "sample_id": 46,
      "difficulty": "unknown",
      "question_type": "group",
      "true_answer": "B, J",
      "prediction": "J",
      "correct": false,
      "response": "Final Answer: J \n"
    },
    {
      "sample_id": 48,
      "difficulty": "unknown",
      "question_type": "group",
      "true_answer": "B, C, D, F",
      "prediction": "B",
      "correct": false,
      "response": "Final Answer: B \n"
    },
    {
      "sample_id": 44,
      "difficulty": "unknown",
      "question_type": "group",
      "true_answer": "C, D, F, H, I",
      "prediction": "C, H, I",
      "correct": false,
      "response": "Final Answer: C, H, I \n"
    },
    {
      "sample_id": 42,
      "difficulty": "unknown",
      "question_type": "group",
      "true_answer": "D, H, I, J",
      "prediction": "D, E, H, I, J",
      "correct": false,
      "response": "Final Answer: D, E, H, I, J \n"
    },
    {
      "sample_id": 49,
      "difficulty": "unknown",
      "question_type": "group",
      "true_answer": "A, F, H",
      "prediction": "A",
      "correct": false,
      "response": "Final Answer: A \n"
    },
    {
      "sample_id": 45,
      "difficulty": "unknown",
      "question_type": "group",
      "true_answer": "A, F",
      "prediction": "A, F, E",
      "correct": false,
      "response": "Final Answer: A, F, E \n"
    },
    {
      "sample_id": 47,
      "difficulty": "unknown",
      "question_type": "group",
      "true_answer": "C, D, G, H, I",
      "prediction": "C, D, G, H, I",
      "correct": true,
      "response": "Final Answer: C, D, G, H, I \n"
    },
    {
      "sample_id": 50,
      "difficulty": "unknown",
      "question_type": "group",
      "true_answer": "F",
      "prediction": "F",
      "correct": true,
      "response": "Final Answer: F \n"
    },
    {
      "sample_id": 51,
      "difficulty": "unknown",
      "question_type": "group",
      "true_answer": "D, G, H, I",
      "prediction": "D, G, H, I",
      "correct": true,
      "response": "Final Answer: D, G, H, I \n"
    },
    {
      "sample_id": 52,
      "difficulty": "unknown",
      "question_type": "group",
      "true_answer": "B, E, F, G",
      "prediction": "B, F",
      "correct": false,
      "response": "Final Answer: B, F \n"
    },
    {
      "sample_id": 57,
      "difficulty": "unknown",
      "question_type": "group",
      "true_answer": "F",
      "prediction": "F",
      "correct": true,
      "response": "Final Answer: F \n"
    },
    {
      "sample_id": 53,
      "difficulty": "unknown",
      "question_type": "group",
      "true_answer": "C, F, H, J",
      "prediction": "C, H, J",
      "correct": false,
      "response": "Final Answer: C, H, J \n"
    },
    {
      "sample_id": 58,
      "difficulty": "unknown",
      "question_type": "group",
      "true_answer": "A, C, E, G",
      "prediction": "A",
      "correct": false,
      "response": "Final Answer: A \n"
    },
    {
      "sample_id": 55,
      "difficulty": "unknown",
      "question_type": "group",
      "true_answer": "F",
      "prediction": "F",
      "correct": true,
      "response": "Final Answer: F \n"
    },
    {
      "sample_id": 56,
      "difficulty": "unknown",
      "question_type": "group",
      "true_answer": "B, G",
      "prediction": "B, G",
      "correct": true,
      "response": "Final Answer: B, G \n"
    },
    {
      "sample_id": 54,
      "difficulty": "unknown",
      "question_type": "group",
      "true_answer": "E, F, H, I",
      "prediction": "E, F, H, I",
      "correct": true,
      "response": "Final Answer: E, F, H, I \n"
    },
    {
      "sample_id": 59,
      "difficulty": "unknown",
      "question_type": "group",
      "true_answer": "B, D, F",
      "prediction": "B, D, F",
      "correct": true,
      "response": "Final Answer: B, D, F \n"
    },
    {
      "sample_id": 60,
      "difficulty": "unknown",
      "question_type": "group",
      "true_answer": "A, E, I",
      "prediction": "A, E, I",
      "correct": true,
      "response": "Final Answer: A, E, I \n"
    },
    {
      "sample_id": 61,
      "difficulty": "unknown",
      "question_type": "group",
      "true_answer": "A, F",
      "prediction": "A",
      "correct": false,
      "response": "Final Answer: A \n"
    },
    {
      "sample_id": 62,
      "difficulty": "unknown",
      "question_type": "group",
      "true_answer": "H",
      "prediction": "H",
      "correct": true,
      "response": "Final Answer: H \n"
    },
    {
      "sample_id": 63,
      "difficulty": "unknown",
      "question_type": "group",
      "true_answer": "D, E, F",
      "prediction": "E",
      "correct": false,
      "response": "Final Answer: E \n"
    },
    {
      "sample_id": 69,
      "difficulty": "unknown",
      "question_type": "group",
      "true_answer": "D, J",
      "prediction": "J",
      "correct": false,
      "response": "Final Answer: J \n"
    },
    {
      "sample_id": 66,
      "difficulty": "unknown",
      "question_type": "group",
      "true_answer": "B, G",
      "prediction": "B",
      "correct": false,
      "response": "Final Answer: B \n"
    },
    {
      "sample_id": 68,
      "difficulty": "unknown",
      "question_type": "group",
      "true_answer": "A, E, G, H",
      "prediction": "A",
      "correct": false,
      "response": "Final Answer: A \n"
    },
    {
      "sample_id": 64,
      "difficulty": "unknown",
      "question_type": "group",
      "true_answer": "B, G",
      "prediction": "B, G",
      "correct": true,
      "response": "Final Answer: B, G \n"
    },
    {
      "sample_id": 65,
      "difficulty": "unknown",
      "question_type": "group",
      "true_answer": "A, E, F",
      "prediction": "A, E",
      "correct": false,
      "response": "Final Answer: A, E \n"
    },
    {
      "sample_id": 67,
      "difficulty": "unknown",
      "question_type": "group",
      "true_answer": "B, C, D, G, H",
      "prediction": "B, C, D, G, H",
      "correct": true,
      "response": "Final Answer: B, C, D, G, H \n"
    },
    {
      "sample_id": 70,
      "difficulty": "unknown",
      "question_type": "group",
      "true_answer": "A, B, E",
      "prediction": "A, E",
      "correct": false,
      "response": "Final Answer: A, E \n"
    },
    {
      "sample_id": 71,
      "difficulty": "unknown",
      "question_type": "group",
      "true_answer": "B, E, H",
      "prediction": "H",
      "correct": false,
      "response": "Final Answer: H \n"
    },
    {
      "sample_id": 72,
      "difficulty": "unknown",
      "question_type": "group",
      "true_answer": "C, E, H, I",
      "prediction": "A, C",
      "correct": false,
      "response": "Final Answer: A, C \n"
    },
    {
      "sample_id": 74,
      "difficulty": "unknown",
      "question_type": "group",
      "true_answer": "F",
      "prediction": "F",
      "correct": true,
      "response": "Final Answer: F \n"
    },
    {
      "sample_id": 73,
      "difficulty": "unknown",
      "question_type": "group",
      "true_answer": "D, G, H",
      "prediction": "D, G, H",
      "correct": true,
      "response": "Final Answer: D, G, H \n"
    },
    {
      "sample_id": 76,
      "difficulty": "unknown",
      "question_type": "group",
      "true_answer": "A, D, F",
      "prediction": "A, F",
      "correct": false,
      "response": "Final Answer: A, F \n"
    },
    {
      "sample_id": 77,
      "difficulty": "unknown",
      "question_type": "group",
      "true_answer": "B, C, E, F",
      "prediction": "B",
      "correct": false,
      "response": "Final Answer: B \n"
    },
    {
      "sample_id": 78,
      "difficulty": "unknown",
      "question_type": "group",
      "true_answer": "B, C, D",
      "prediction": "C",
      "correct": false,
      "response": "Final Answer: C \n"
    },
    {
      "sample_id": 75,
      "difficulty": "unknown",
      "question_type": "group",
      "true_answer": "E, G, H",
      "prediction": "H",
      "correct": false,
      "response": "Final Answer: H \n"
    },
    {
      "sample_id": 80,
      "difficulty": "unknown",
      "question_type": "group",
      "true_answer": "C, G, J",
      "prediction": "J",
      "correct": false,
      "response": "Final Answer: J \n"
    },
    {
      "sample_id": 79,
      "difficulty": "unknown",
      "question_type": "group",
      "true_answer": "C, E, H, I",
      "prediction": "C, J",
      "correct": false,
      "response": "Final Answer: C, J \n"
    },
    {
      "sample_id": 81,
      "difficulty": "unknown",
      "question_type": "group",
      "true_answer": "B, E",
      "prediction": "E",
      "correct": false,
      "response": "Final Answer: E \n"
    },
    {
      "sample_id": 82,
      "difficulty": "unknown",
      "question_type": "group",
      "true_answer": "I",
      "prediction": "I",
      "correct": true,
      "response": "Final Answer: I \n"
    },
    {
      "sample_id": 86,
      "difficulty": "unknown",
      "question_type": "group",
      "true_answer": "A, B, C, E",
      "prediction": "A",
      "correct": false,
      "response": "Final Answer: A \n"
    },
    {
      "sample_id": 83,
      "difficulty": "unknown",
      "question_type": "group",
      "true_answer": "B, C, F, G, H",
      "prediction": "B, C, F, G, H",
      "correct": true,
      "response": "Final Answer: B, C, F, G, H \n"
    },
    {
      "sample_id": 85,
      "difficulty": "unknown",
      "question_type": "group",
      "true_answer": "F",
      "prediction": "F",
      "correct": true,
      "response": "Final Answer: F \n"
    },
    {
      "sample_id": 84,
      "difficulty": "unknown",
      "question_type": "group",
      "true_answer": "A, B, H",
      "prediction": "A, B",
      "correct": false,
      "response": "Final Answer: A, B \n"
    },
    {
      "sample_id": 87,
      "difficulty": "unknown",
      "question_type": "group",
      "true_answer": "E, I",
      "prediction": "E",
      "correct": false,
      "response": "Final Answer: E \n"
    },
    {
      "sample_id": 89,
      "difficulty": "unknown",
      "question_type": "group",
      "true_answer": "C, F, H",
      "prediction": "C, F",
      "correct": false,
      "response": "Final Answer: C, F \n"
    },
    {
      "sample_id": 88,
      "difficulty": "unknown",
      "question_type": "group",
      "true_answer": "E, G, H",
      "prediction": "E, G, H",
      "correct": true,
      "response": "Final Answer: E, G, H \n"
    },
    {
      "sample_id": 90,
      "difficulty": "unknown",
      "question_type": "group",
      "true_answer": "D, I",
      "prediction": "I",
      "correct": false,
      "response": "Final Answer: I \n"
    },
    {
      "sample_id": 91,
      "difficulty": "unknown",
      "question_type": "group",
      "true_answer": "D, G",
      "prediction": "D, G",
      "correct": true,
      "response": "Final Answer: D, G \n"
    },
    {
      "sample_id": 92,
      "difficulty": "unknown",
      "question_type": "group",
      "true_answer": "A, C, F, G, I, J",
      "prediction": "A, J, I",
      "correct": false,
      "response": "Final Answer: A, J, I \n"
    },
    {
      "sample_id": 94,
      "difficulty": "unknown",
      "question_type": "group",
      "true_answer": "B, C, G, H, I",
      "prediction": "B",
      "correct": false,
      "response": "Final Answer: B \n"
    },
    {
      "sample_id": 96,
      "difficulty": "unknown",
      "question_type": "group",
      "true_answer": "C, E, F",
      "prediction": "C",
      "correct": false,
      "response": "Final Answer: C \n"
    },
    {
      "sample_id": 97,
      "difficulty": "unknown",
      "question_type": "group",
      "true_answer": "A, B, E, F",
      "prediction": "A",
      "correct": false,
      "response": "Final Answer: A \n"
    },
    {
      "sample_id": 93,
      "difficulty": "unknown",
      "question_type": "group",
      "true_answer": "A, F",
      "prediction": "A, F",
      "correct": true,
      "response": "Final Answer: A, F \n"
    },
    {
      "sample_id": 95,
      "difficulty": "unknown",
      "question_type": "group",
      "true_answer": "B, C, E",
      "prediction": "B",
      "correct": false,
      "response": "Final Answer: B \n"
    },
    {
      "sample_id": 99,
      "difficulty": "unknown",
      "question_type": "group",
      "true_answer": "D, E, G",
      "prediction": "D",
      "correct": false,
      "response": "Final Answer: D \n"
    },
    {
      "sample_id": 98,
      "difficulty": "unknown",
      "question_type": "group",
      "true_answer": "B, C, D, F, I",
      "prediction": "B, F, I",
      "correct": false,
      "response": "Final Answer: B, F, I \n"
    }
  ]
}